PyArpes/__init__.py
PyArpes/show.py
PyArpes-0.0.2.dist-info/METADATA
PyArpes-0.0.2.dist-info/WHEEL
PyArpes-0.0.2.dist-info/top_level.txt
PyArpes-0.0.2.dist-info/RECORD
