Metadata-Version: 2.1
Name: PyArpes
Version: 0.0.2
Summary: Data Post-Processing Package for ARPES Data
Home-page: https://github.com/Bin-Cao/PyArpes
Author: CaoBin
Author-email: bcao686@connect.hkust-gz.edu.cn
Maintainer: CaoBin
Maintainer-email: bcao686@connect.hkust-gz.edu.cn
License: MIT License
Classifier: Development Status :: 3 - Alpha
Classifier: Intended Audience :: Developers
Classifier: Topic :: Software Development :: Build Tools
Classifier: License :: OSI Approved :: MIT License
Classifier: Programming Language :: Python :: 3
Requires-Python: >=3.5
